<annotation>
	<folder>nonhuman1</folder>
	<filename>img (198).jpg</filename>
	<path>F:\NITD\Project\Images\My_dataset\nonhuman1\img (198).jpg</path>
	<source>
		<database>Unknown</database>
	</source>
	<size>
		<width>225</width>
		<height>225</height>
		<depth>3</depth>
	</size>
	<segmented>0</segmented>
	<object>
		<name>nonhuman</name>
		<pose>Unspecified</pose>
		<truncated>0</truncated>
		<difficult>0</difficult>
		<bndbox>
			<xmin>49</xmin>
			<ymin>4</ymin>
			<xmax>114</xmax>
			<ymax>219</ymax>
		</bndbox>
	</object>
	<object>
		<name>nonhuman</name>
		<pose>Unspecified</pose>
		<truncated>0</truncated>
		<difficult>0</difficult>
		<bndbox>
			<xmin>113</xmin>
			<ymin>13</ymin>
			<xmax>177</xmax>
			<ymax>213</ymax>
		</bndbox>
	</object>
</annotation>
